{
  "MoviesFunction": {
    "DATABASE_HOST": "localhost",
    "DATABASE_PORT": "5432",
    "DATABASE_NAME": "bms_production", 
    "DATABASE_USER": "bms_user",
    "DATABASE_PASSWORD": "temp-password",
    "REDIS_HOST": "localhost",
    "REDIS_PORT": "6379",
    "SQS_QUEUE_URL": "https://sqs.ap-south-1.amazonaws.com/123456789012/bms-events-queue",
    "HOLD_TTL_SECONDS": "300",
    "ORDER_TTL_SECONDS": "300",
    "MAX_SEATS_PER_BOOKING": "10",
    "AWS_REGION": "ap-south-1"
  },
  "SeatsFunction": {
    "DATABASE_HOST": "localhost", 
    "DATABASE_PORT": "5432",
    "DATABASE_NAME": "bms_production",
    "DATABASE_USER": "bms_user", 
    "DATABASE_PASSWORD": "temp-password",
    "REDIS_HOST": "localhost",
    "REDIS_PORT": "6379",
    "SQS_QUEUE_URL": "https://sqs.ap-south-1.amazonaws.com/123456789012/bms-events-queue",
    "HOLD_TTL_SECONDS": "300",
    "ORDER_TTL_SECONDS": "300", 
    "MAX_SEATS_PER_BOOKING": "10",
    "AWS_REGION": "ap-south-1"
  },
  "OrdersFunction": {
    "DATABASE_HOST": "localhost",
    "DATABASE_PORT": "5432", 
    "DATABASE_NAME": "bms_production",
    "DATABASE_USER": "bms_user",
    "DATABASE_PASSWORD": "temp-password",
    "REDIS_HOST": "localhost",
    "REDIS_PORT": "6379",
    "SQS_QUEUE_URL": "https://sqs.ap-south-1.amazonaws.com/123456789012/bms-events-queue",
    "HOLD_TTL_SECONDS": "300",
    "ORDER_TTL_SECONDS": "300",
    "MAX_SEATS_PER_BOOKING": "10", 
    "AWS_REGION": "ap-south-1"
  },
  "EventsFunction": {
    "SQS_QUEUE_URL": "https://sqs.ap-south-1.amazonaws.com/123456789012/bms-events-queue",
    "AWS_REGION": "ap-south-1"
  }
}